pyplatypus/__init__.py
pyplatypus/engine.py
pyplatypus/config/__init__.py
pyplatypus/config/augmentation_config.py
pyplatypus/config/input_config.py
pyplatypus/config/segmentation_constants.py
pyplatypus/data_models/__init__.py
pyplatypus/data_models/augmentation_datamodel.py
pyplatypus/data_models/callbacks_datamodel.py
pyplatypus/data_models/object_detection_datamodel.py
pyplatypus/data_models/optimizer_datamodel.py
pyplatypus/data_models/platypus_engine_datamodel.py
pyplatypus/data_models/semantic_segmentation_datamodel.py
pyplatypus/data_models/semantic_segmentation_loss_datamodel.py
pyplatypus/object_detection/__init__.py
pyplatypus/segmentation/__init__.py
pyplatypus/segmentation/extended_loss_functions.py
pyplatypus/segmentation/generator.py
pyplatypus/segmentation/loss_functions.py
pyplatypus/segmentation/models/__init__.py
pyplatypus/segmentation/models/u_shaped_models.py
pyplatypus/solvers/__init__.py
pyplatypus/solvers/platypus_cv_solver.py
pyplatypus/utils/__init__.py
pyplatypus/utils/augmentation_toolbox.py
pyplatypus/utils/config_processing_functions.py
pyplatypus/utils/extended_tensorflow_callbacks.py
pyplatypus/utils/lovasz_softmax.py
pyplatypus/utils/prediction_utils.py
pyplatypus/utils/prepare_loss_metrics.py
pyplatypus/utils/toolbox.py
tests/__init__.py
pyplatypus-0.1.0rc2.dist-info/LICENSE
pyplatypus-0.1.0rc2.dist-info/METADATA
pyplatypus-0.1.0rc2.dist-info/WHEEL
pyplatypus-0.1.0rc2.dist-info/top_level.txt
pyplatypus-0.1.0rc2.dist-info/RECORD
