Metadata-Version: 2.1
Name: pyplatypus
Version: 0.1.0rc2
Summary: Set of tools for Computer Vision handling the object detection and image
Home-page: https://github.com/maju116/pyplatypus
Author: Michał Maj, Jakub Borkowski
Author-email: michalmaj116@gmail.com, jakub.borkowski@chionis.co
License: UNKNOWN
Project-URL: Bug Tracker, https://github.com/maju116/pyplatypus/issues
Platform: UNKNOWN
Classifier: Programming Language :: Python :: 3
Classifier: License :: OSI Approved :: MIT License
Classifier: Operating System :: OS Independent
Requires-Python: >=3.6
License-File: LICENSE
Requires-Dist: tensorflow (==2.9.1)
Requires-Dist: albumentations (==1.1.0)
Requires-Dist: Keras-Preprocessing (==1.1.2)
Requires-Dist: scikit-image (==0.19.1)
Requires-Dist: scikit-learn (==1.0.2)
Requires-Dist: scipy (==1.8.1)
Requires-Dist: tensorflow-estimator (==2.9.0)
Requires-Dist: pandas (==1.3.1)
Requires-Dist: numpy (==1.22.4)
Requires-Dist: tensorboard (==2.9.0)
Requires-Dist: PyYAML (==6.0)
Requires-Dist: pydicom (==2.2.0)
Requires-Dist: pydantic (==1.9.1)
